{
    "1H": {
        "btc": 0.23,
        "alt_mean": 0.68,
        "alt_median": 0.54
    },
    "24H": {
        "btc": 3.69,
        "alt_mean": 9.26,
        "alt_median": 8.89
    },
    "7D": {
        "btc": 6.5,
        "alt_mean": 11.81,
        "alt_median": 10.58
    },
    "30D": {
        "btc": 33.62,
        "alt_mean": 37.53,
        "alt_median": 36.28
    },
    "200D": {
        "btc": 51.26,
        "alt_mean": 36.86,
        "alt_median": 4.11
    },
    "1Y": {
        "btc": 69.41,
        "alt_mean": 42.47,
        "alt_median": 0.24
    },
    "time": "May 09 2025 11:09:12"
}