{
    "1H": {
        "btc": -0.04,
        "alt_mean": -0.03,
        "alt_median": -0.0
    },
    "24H": {
        "btc": -3.48,
        "alt_mean": -1.49,
        "alt_median": -1.89
    },
    "7D": {
        "btc": 3.23,
        "alt_mean": 0.96,
        "alt_median": 0.01
    },
    "30D": {
        "btc": -4.54,
        "alt_mean": -1.27,
        "alt_median": -0.0
    },
    "200D": {
        "btc": -40.71,
        "alt_mean": -18.46,
        "alt_median": -23.08
    },
    "1Y": {
        "btc": -21.97,
        "alt_mean": -8.89,
        "alt_median": -2.9
    },
    "time": "Mar 07 2026 04:54:41"
}