{
    "1H": {
        "btc": -1.32,
        "alt_mean": -1.01,
        "alt_median": -0.99
    },
    "24H": {
        "btc": 4.63,
        "alt_mean": 0.63,
        "alt_median": 0.68
    },
    "7D": {
        "btc": 8.95,
        "alt_mean": 6.17,
        "alt_median": 5.83
    },
    "30D": {
        "btc": -31.67,
        "alt_mean": -16.4,
        "alt_median": -18.35
    },
    "200D": {
        "btc": -54.36,
        "alt_mean": -54.92,
        "alt_median": -65.56
    },
    "1Y": {
        "btc": -37.04,
        "alt_mean": -27.85,
        "alt_median": -45.91
    },
    "time": "Jul 08 2022 13:29:09"
}