{
    "1H": {
        "btc": -1.64,
        "alt_mean": -2.73,
        "alt_median": -2.69
    },
    "24H": {
        "btc": 0.46,
        "alt_mean": 0.61,
        "alt_median": 0.5
    },
    "7D": {
        "btc": -7.39,
        "alt_mean": 0.26,
        "alt_median": -6.47
    },
    "30D": {
        "btc": -4.95,
        "alt_mean": 42.69,
        "alt_median": 22.94
    },
    "200D": {
        "btc": 422.05,
        "alt_mean": 839.32,
        "alt_median": 451.71
    },
    "1Y": {
        "btc": 678.45,
        "alt_mean": 2448.11,
        "alt_median": 897.59
    },
    "time": "Apr 20 2021 15:10:04"
}