{
    "1H": {
        "btc": 0.26,
        "alt_mean": 0.44,
        "alt_median": 0.27
    },
    "24H": {
        "btc": 0.92,
        "alt_mean": -0.37,
        "alt_median": -0.87
    },
    "7D": {
        "btc": 2.77,
        "alt_mean": 5.87,
        "alt_median": 4.53
    },
    "30D": {
        "btc": 28.24,
        "alt_mean": 17.09,
        "alt_median": 11.44
    },
    "200D": {
        "btc": 14.8,
        "alt_mean": -7.12,
        "alt_median": -15.65
    },
    "1Y": {
        "btc": 72.39,
        "alt_mean": 17.94,
        "alt_median": 0.03
    },
    "time": "Nov 02 2023 20:07:46"
}