{
    "1H": {
        "btc": 0.15,
        "alt_mean": 0.06,
        "alt_median": 0.02
    },
    "24H": {
        "btc": 6.82,
        "alt_mean": 4.09,
        "alt_median": 3.11
    },
    "7D": {
        "btc": 13.3,
        "alt_mean": 17.93,
        "alt_median": 17.35
    },
    "30D": {
        "btc": -1.39,
        "alt_mean": 44.47,
        "alt_median": 38.6
    },
    "200D": {
        "btc": 402.47,
        "alt_mean": 901.01,
        "alt_median": 527.82
    },
    "1Y": {
        "btc": 573.59,
        "alt_mean": 2353.87,
        "alt_median": 712.7
    },
    "time": "May 01 2021 06:08:42"
}