{
    "1H": {
        "btc": -0.86,
        "alt_mean": -1.42,
        "alt_median": -1.53
    },
    "24H": {
        "btc": -3.67,
        "alt_mean": -5.63,
        "alt_median": -6.11
    },
    "7D": {
        "btc": -3.91,
        "alt_mean": -8.27,
        "alt_median": -11.01
    },
    "30D": {
        "btc": -1.25,
        "alt_mean": -9.44,
        "alt_median": -8.61
    },
    "200D": {
        "btc": -49.36,
        "alt_mean": -55.7,
        "alt_median": -65.92
    },
    "1Y": {
        "btc": -22.63,
        "alt_mean": -15.23,
        "alt_median": -37.26
    },
    "time": "Jun 11 2022 13:16:39"
}