{
    "1H": {
        "btc": -0.85,
        "alt_mean": -0.68,
        "alt_median": -0.64
    },
    "24H": {
        "btc": -0.75,
        "alt_mean": 0.29,
        "alt_median": -0.4
    },
    "7D": {
        "btc": -3.83,
        "alt_mean": -0.13,
        "alt_median": -2.05
    },
    "30D": {
        "btc": 7.81,
        "alt_mean": 6.79,
        "alt_median": 1.77
    },
    "200D": {
        "btc": 87.61,
        "alt_mean": 136.49,
        "alt_median": 68.78
    },
    "1Y": {
        "btc": 154.49,
        "alt_mean": 187.54,
        "alt_median": 105.14
    },
    "time": "May 28 2024 01:53:05"
}