{
    "1H": {
        "btc": 0.63,
        "alt_mean": 1.04,
        "alt_median": 1.12
    },
    "24H": {
        "btc": -2.24,
        "alt_mean": -6.64,
        "alt_median": -7.18
    },
    "7D": {
        "btc": 10.43,
        "alt_mean": -0.8,
        "alt_median": -1.78
    },
    "30D": {
        "btc": 12.64,
        "alt_mean": -5.03,
        "alt_median": -5.83
    },
    "200D": {
        "btc": 21.03,
        "alt_mean": 4.41,
        "alt_median": 0.0
    },
    "1Y": {
        "btc": -38.15,
        "alt_mean": -36.35,
        "alt_median": -44.54
    },
    "time": "Mar 15 2023 19:06:46"
}