{
    "1H": {
        "btc": -0.15,
        "alt_mean": -0.06,
        "alt_median": -0.09
    },
    "24H": {
        "btc": 4.81,
        "alt_mean": 2.76,
        "alt_median": 2.47
    },
    "7D": {
        "btc": 4.98,
        "alt_mean": 3.27,
        "alt_median": 3.46
    },
    "30D": {
        "btc": -4.37,
        "alt_mean": -5.25,
        "alt_median": -5.53
    },
    "200D": {
        "btc": 75.99,
        "alt_mean": 25.14,
        "alt_median": 11.41
    },
    "1Y": {
        "btc": -3.12,
        "alt_mean": 4.36,
        "alt_median": -3.9
    },
    "time": "May 28 2023 23:06:57"
}