{
    "1H": {
        "btc": -0.38,
        "alt_mean": -0.56,
        "alt_median": -0.62
    },
    "24H": {
        "btc": -1.55,
        "alt_mean": 1.32,
        "alt_median": 0.17
    },
    "7D": {
        "btc": 12.68,
        "alt_mean": 26.82,
        "alt_median": 22.88
    },
    "30D": {
        "btc": -3.93,
        "alt_mean": 41.79,
        "alt_median": 29.66
    },
    "200D": {
        "btc": 394.41,
        "alt_mean": 883.6,
        "alt_median": 513.09
    },
    "1Y": {
        "btc": 540.14,
        "alt_mean": 2224.54,
        "alt_median": 698.52
    },
    "time": "May 02 2021 09:07:01"
}