{
    "1H": {
        "btc": -0.35,
        "alt_mean": -0.98,
        "alt_median": -1.11
    },
    "24H": {
        "btc": -0.73,
        "alt_mean": -4.46,
        "alt_median": -4.85
    },
    "7D": {
        "btc": -5.06,
        "alt_mean": -13.09,
        "alt_median": -15.5
    },
    "30D": {
        "btc": -2.13,
        "alt_mean": 12.14,
        "alt_median": -0.16
    },
    "200D": {
        "btc": 36.41,
        "alt_mean": 43.21,
        "alt_median": 3.54
    },
    "1Y": {
        "btc": 119.79,
        "alt_mean": 118.23,
        "alt_median": 53.79
    },
    "time": "Dec 22 2024 03:18:18"
}