{
    "1H": {
        "btc": -0.37,
        "alt_mean": -0.48,
        "alt_median": -0.53
    },
    "24H": {
        "btc": 2.78,
        "alt_mean": 1.66,
        "alt_median": 0.6
    },
    "7D": {
        "btc": 9.18,
        "alt_mean": 11.42,
        "alt_median": 12.03
    },
    "30D": {
        "btc": 16.77,
        "alt_mean": 18.07,
        "alt_median": 15.27
    },
    "200D": {
        "btc": -13.4,
        "alt_mean": 5.28,
        "alt_median": -18.11
    },
    "1Y": {
        "btc": -14.77,
        "alt_mean": 127.57,
        "alt_median": 48.31
    },
    "time": "Mar 25 2022 15:08:19"
}