{
    "1H": {
        "btc": 1.26,
        "alt_mean": 1.42,
        "alt_median": 1.33
    },
    "24H": {
        "btc": -5.24,
        "alt_mean": -7.0,
        "alt_median": -8.35
    },
    "7D": {
        "btc": -2.55,
        "alt_mean": 5.76,
        "alt_median": -0.82
    },
    "30D": {
        "btc": -7.07,
        "alt_mean": 48.95,
        "alt_median": 20.91
    },
    "200D": {
        "btc": 330.39,
        "alt_mean": 1024.04,
        "alt_median": 620.58
    },
    "1Y": {
        "btc": 536.84,
        "alt_mean": 2613.58,
        "alt_median": 913.44
    },
    "time": "May 11 2021 11:05:15"
}