{
    "1H": {
        "btc": 0.11,
        "alt_mean": 0.1,
        "alt_median": 0.09
    },
    "24H": {
        "btc": -0.11,
        "alt_mean": -0.83,
        "alt_median": -0.64
    },
    "7D": {
        "btc": -2.44,
        "alt_mean": -4.82,
        "alt_median": -4.94
    },
    "30D": {
        "btc": 3.37,
        "alt_mean": 0.62,
        "alt_median": 0.04
    },
    "200D": {
        "btc": -3.64,
        "alt_mean": -13.26,
        "alt_median": -21.45
    },
    "1Y": {
        "btc": 40.43,
        "alt_mean": -2.23,
        "alt_median": -3.88
    },
    "time": "Oct 13 2023 07:07:09"
}