{
    "1H": {
        "btc": -0.16,
        "alt_mean": -0.22,
        "alt_median": -0.2
    },
    "24H": {
        "btc": 0.97,
        "alt_mean": 0.68,
        "alt_median": 0.17
    },
    "7D": {
        "btc": -3.0,
        "alt_mean": -5.3,
        "alt_median": -6.32
    },
    "30D": {
        "btc": -0.47,
        "alt_mean": -1.11,
        "alt_median": -2.21
    },
    "200D": {
        "btc": -2.98,
        "alt_mean": -9.04,
        "alt_median": -15.54
    },
    "1Y": {
        "btc": -45.21,
        "alt_mean": -38.82,
        "alt_median": -49.3
    },
    "time": "Mar 01 2023 19:07:05"
}