{
    "1H": {
        "btc": -0.65,
        "alt_mean": -0.44,
        "alt_median": -0.26
    },
    "24H": {
        "btc": 6.09,
        "alt_mean": 6.56,
        "alt_median": 5.24
    },
    "7D": {
        "btc": 25.4,
        "alt_mean": 25.21,
        "alt_median": 20.61
    },
    "30D": {
        "btc": 77.96,
        "alt_mean": 44.5,
        "alt_median": 24.74
    },
    "200D": {
        "btc": 269.29,
        "alt_mean": 194.54,
        "alt_median": 86.92
    },
    "1Y": {
        "btc": 367.91,
        "alt_mean": 522.26,
        "alt_median": 123.73
    },
    "time": "Jan 06 2021 15:08:14"
}