{
    "1H": {
        "btc": -0.14,
        "alt_mean": 0.07,
        "alt_median": -0.03
    },
    "24H": {
        "btc": -0.27,
        "alt_mean": -1.13,
        "alt_median": -0.92
    },
    "7D": {
        "btc": 2.32,
        "alt_mean": 0.61,
        "alt_median": -0.13
    },
    "30D": {
        "btc": 14.37,
        "alt_mean": 67.39,
        "alt_median": 34.33
    },
    "200D": {
        "btc": 46.72,
        "alt_mean": 73.02,
        "alt_median": 34.22
    },
    "1Y": {
        "btc": 145.08,
        "alt_mean": 188.53,
        "alt_median": 128.65
    },
    "time": "Dec 13 2024 12:19:50"
}