{
    "1H": {
        "btc": 0.09,
        "alt_mean": 0.05,
        "alt_median": 0.03
    },
    "24H": {
        "btc": 1.05,
        "alt_mean": 1.0,
        "alt_median": 1.01
    },
    "7D": {
        "btc": -0.62,
        "alt_mean": -1.51,
        "alt_median": -0.8
    },
    "30D": {
        "btc": -7.09,
        "alt_mean": -7.39,
        "alt_median": -8.79
    },
    "200D": {
        "btc": 29.46,
        "alt_mean": -9.53,
        "alt_median": -9.91
    },
    "1Y": {
        "btc": -7.93,
        "alt_mean": 1.94,
        "alt_median": -7.98
    },
    "time": "May 27 2023 02:29:59"
}