{
    "1H": {
        "btc": -0.76,
        "alt_mean": -1.55,
        "alt_median": -1.54
    },
    "24H": {
        "btc": 0.73,
        "alt_mean": 0.06,
        "alt_median": -0.0
    },
    "7D": {
        "btc": -0.51,
        "alt_mean": -4.8,
        "alt_median": -3.67
    },
    "30D": {
        "btc": 22.94,
        "alt_mean": 23.18,
        "alt_median": 16.51
    },
    "200D": {
        "btc": 44.67,
        "alt_mean": 41.77,
        "alt_median": 6.61
    },
    "1Y": {
        "btc": 55.13,
        "alt_mean": 37.76,
        "alt_median": -0.04
    },
    "time": "May 18 2025 20:11:54"
}