{
    "1H": {
        "btc": -0.3,
        "alt_mean": -1.04,
        "alt_median": -1.08
    },
    "24H": {
        "btc": -0.2,
        "alt_mean": -1.07,
        "alt_median": -1.01
    },
    "7D": {
        "btc": -8.98,
        "alt_mean": -17.16,
        "alt_median": -20.16
    },
    "30D": {
        "btc": -7.78,
        "alt_mean": -17.31,
        "alt_median": -16.7
    },
    "200D": {
        "btc": 133.19,
        "alt_mean": 143.69,
        "alt_median": 81.5
    },
    "1Y": {
        "btc": 111.72,
        "alt_mean": 87.62,
        "alt_median": 50.17
    },
    "time": "Apr 17 2024 12:14:22"
}