{
    "1H": {
        "btc": 0.34,
        "alt_mean": 0.22,
        "alt_median": 0.21
    },
    "24H": {
        "btc": 1.57,
        "alt_mean": 4.1,
        "alt_median": 3.4
    },
    "7D": {
        "btc": -1.78,
        "alt_mean": -3.43,
        "alt_median": -3.82
    },
    "30D": {
        "btc": 6.75,
        "alt_mean": 4.04,
        "alt_median": 0.43
    },
    "200D": {
        "btc": -15.01,
        "alt_mean": 56.7,
        "alt_median": -0.3
    },
    "1Y": {
        "btc": -16.24,
        "alt_mean": 211.92,
        "alt_median": 24.02
    },
    "time": "Feb 26 2022 20:07:50"
}