{
    "1H": {
        "btc": 0.45,
        "alt_mean": -0.08,
        "alt_median": -0.15
    },
    "24H": {
        "btc": -9.73,
        "alt_mean": -8.66,
        "alt_median": -10.15
    },
    "7D": {
        "btc": -0.56,
        "alt_mean": 3.01,
        "alt_median": 0.65
    },
    "30D": {
        "btc": 31.68,
        "alt_mean": 64.79,
        "alt_median": 36.73
    },
    "200D": {
        "btc": 292.62,
        "alt_mean": 314.02,
        "alt_median": 170.62
    },
    "1Y": {
        "btc": 433.52,
        "alt_mean": 798.19,
        "alt_median": 247.27
    },
    "time": "Mar 05 2021 02:18:01"
}