{
    "1H": {
        "btc": 0.08,
        "alt_mean": 0.05,
        "alt_median": 0.01
    },
    "24H": {
        "btc": -0.6,
        "alt_mean": -0.74,
        "alt_median": -0.15
    },
    "7D": {
        "btc": 2.7,
        "alt_mean": 0.43,
        "alt_median": 0.02
    },
    "30D": {
        "btc": -19.73,
        "alt_mean": -2.89,
        "alt_median": -7.61
    },
    "200D": {
        "btc": -28.92,
        "alt_mean": -15.25,
        "alt_median": -14.82
    },
    "1Y": {
        "btc": -39.07,
        "alt_mean": -18.34,
        "alt_median": -5.29
    },
    "time": "Jun 14 2026 19:08:48"
}