{
    "1H": {
        "btc": 0.16,
        "alt_mean": -0.62,
        "alt_median": -0.81
    },
    "24H": {
        "btc": 2.38,
        "alt_mean": 5.58,
        "alt_median": 3.93
    },
    "7D": {
        "btc": -1.94,
        "alt_mean": 0.24,
        "alt_median": -2.32
    },
    "30D": {
        "btc": 16.85,
        "alt_mean": 68.08,
        "alt_median": 38.48
    },
    "200D": {
        "btc": 46.09,
        "alt_mean": 76.81,
        "alt_median": 38.31
    },
    "1Y": {
        "btc": 141.3,
        "alt_mean": 180.75,
        "alt_median": 119.27
    },
    "time": "Dec 12 2024 14:10:28"
}