{
    "1H": {
        "btc": 0.0,
        "alt_mean": -0.04,
        "alt_median": -0.02
    },
    "24H": {
        "btc": -0.21,
        "alt_mean": 0.95,
        "alt_median": 0.01
    },
    "7D": {
        "btc": -2.14,
        "alt_mean": -3.74,
        "alt_median": -4.31
    },
    "30D": {
        "btc": -2.14,
        "alt_mean": -5.82,
        "alt_median": -2.31
    },
    "200D": {
        "btc": -16.93,
        "alt_mean": -5.71,
        "alt_median": -0.21
    },
    "1Y": {
        "btc": -7.82,
        "alt_mean": -12.04,
        "alt_median": -9.3
    },
    "time": "Dec 20 2025 16:13:27"
}