{
    "1H": {
        "btc": 0.13,
        "alt_mean": 0.41,
        "alt_median": 0.28
    },
    "24H": {
        "btc": -1.42,
        "alt_mean": 0.03,
        "alt_median": 0.04
    },
    "7D": {
        "btc": -11.77,
        "alt_mean": -9.3,
        "alt_median": -7.86
    },
    "30D": {
        "btc": -16.76,
        "alt_mean": -19.29,
        "alt_median": -26.24
    },
    "200D": {
        "btc": 41.68,
        "alt_mean": 71.49,
        "alt_median": 21.36
    },
    "1Y": {
        "btc": 50.58,
        "alt_mean": 50.23,
        "alt_median": 4.39
    },
    "time": "Feb 27 2025 16:13:00"
}