{
    "1H": {
        "btc": 0.23,
        "alt_mean": 0.05,
        "alt_median": 0.11
    },
    "24H": {
        "btc": -1.54,
        "alt_mean": -1.77,
        "alt_median": -1.81
    },
    "7D": {
        "btc": 0.69,
        "alt_mean": 1.01,
        "alt_median": 0.57
    },
    "30D": {
        "btc": -10.12,
        "alt_mean": -9.08,
        "alt_median": -11.36
    },
    "200D": {
        "btc": -55.15,
        "alt_mean": -47.67,
        "alt_median": -56.43
    },
    "1Y": {
        "btc": -65.17,
        "alt_mean": -55.92,
        "alt_median": -64.06
    },
    "time": "Oct 10 2022 17:31:35"
}