{
    "1H": {
        "btc": -0.48,
        "alt_mean": -0.66,
        "alt_median": -0.64
    },
    "24H": {
        "btc": 3.0,
        "alt_mean": 0.52,
        "alt_median": -0.14
    },
    "7D": {
        "btc": 20.71,
        "alt_mean": 4.2,
        "alt_median": -0.0
    },
    "30D": {
        "btc": 27.55,
        "alt_mean": 12.04,
        "alt_median": 0.36
    },
    "200D": {
        "btc": 143.4,
        "alt_mean": 147.8,
        "alt_median": 64.81
    },
    "1Y": {
        "btc": 213.25,
        "alt_mean": 363.94,
        "alt_median": 109.08
    },
    "time": "Dec 23 2020 07:16:34"
}