{
    "1H": {
        "btc": 0.09,
        "alt_mean": 0.04,
        "alt_median": 0.06
    },
    "24H": {
        "btc": 1.49,
        "alt_mean": 2.97,
        "alt_median": 2.43
    },
    "7D": {
        "btc": -3.08,
        "alt_mean": -7.28,
        "alt_median": -8.0
    },
    "30D": {
        "btc": 1.42,
        "alt_mean": 3.14,
        "alt_median": -4.05
    },
    "200D": {
        "btc": 149.77,
        "alt_mean": 237.12,
        "alt_median": 155.3
    },
    "1Y": {
        "btc": 143.65,
        "alt_mean": 179.1,
        "alt_median": 84.53
    },
    "time": "Apr 06 2024 11:05:43"
}