{
    "1H": {
        "btc": 0.85,
        "alt_mean": 0.42,
        "alt_median": 0.37
    },
    "24H": {
        "btc": -2.39,
        "alt_mean": 1.75,
        "alt_median": 0.44
    },
    "7D": {
        "btc": 6.66,
        "alt_mean": 5.96,
        "alt_median": 2.18
    },
    "30D": {
        "btc": 51.73,
        "alt_mean": 33.59,
        "alt_median": 26.06
    },
    "200D": {
        "btc": 5.24,
        "alt_mean": 117.96,
        "alt_median": 16.2
    },
    "1Y": {
        "btc": 378.5,
        "alt_mean": 1919.41,
        "alt_median": 666.18
    },
    "time": "Oct 22 2021 20:07:11"
}