{
    "1H": {
        "btc": 0.4,
        "alt_mean": 0.31,
        "alt_median": 0.24
    },
    "24H": {
        "btc": 1.53,
        "alt_mean": -0.12,
        "alt_median": -0.32
    },
    "7D": {
        "btc": 6.34,
        "alt_mean": 18.79,
        "alt_median": 8.64
    },
    "30D": {
        "btc": 35.51,
        "alt_mean": 37.51,
        "alt_median": 18.43
    },
    "200D": {
        "btc": 47.65,
        "alt_mean": 33.43,
        "alt_median": 1.86
    },
    "1Y": {
        "btc": 149.56,
        "alt_mean": 154.64,
        "alt_median": 77.86
    },
    "time": "Nov 20 2024 08:13:57"
}