{
    "1H": {
        "btc": -0.15,
        "alt_mean": 0.02,
        "alt_median": 0.01
    },
    "24H": {
        "btc": -0.23,
        "alt_mean": -0.21,
        "alt_median": -0.09
    },
    "7D": {
        "btc": -5.84,
        "alt_mean": -4.62,
        "alt_median": -5.48
    },
    "30D": {
        "btc": 3.02,
        "alt_mean": 3.97,
        "alt_median": 1.29
    },
    "200D": {
        "btc": -18.0,
        "alt_mean": 15.03,
        "alt_median": -0.06
    },
    "1Y": {
        "btc": -12.37,
        "alt_mean": -13.47,
        "alt_median": -7.84
    },
    "time": "Jan 23 2026 05:20:10"
}