{
    "1H": {
        "btc": 0.03,
        "alt_mean": 0.23,
        "alt_median": 0.05
    },
    "24H": {
        "btc": -0.5,
        "alt_mean": -0.02,
        "alt_median": -0.01
    },
    "7D": {
        "btc": -5.07,
        "alt_mean": -6.12,
        "alt_median": -6.22
    },
    "30D": {
        "btc": 7.9,
        "alt_mean": 8.51,
        "alt_median": 1.35
    },
    "200D": {
        "btc": 16.98,
        "alt_mean": 13.96,
        "alt_median": -0.18
    },
    "1Y": {
        "btc": 52.52,
        "alt_mean": 27.63,
        "alt_median": -0.03
    },
    "time": "Jun 02 2025 15:12:32"
}