{
    "1H": {
        "btc": 0.75,
        "alt_mean": 0.51,
        "alt_median": 0.48
    },
    "24H": {
        "btc": 1.37,
        "alt_mean": 1.66,
        "alt_median": 1.28
    },
    "7D": {
        "btc": -1.13,
        "alt_mean": -1.07,
        "alt_median": -0.88
    },
    "30D": {
        "btc": -1.81,
        "alt_mean": 8.48,
        "alt_median": 2.37
    },
    "200D": {
        "btc": 74.86,
        "alt_mean": 30.71,
        "alt_median": 14.11
    },
    "1Y": {
        "btc": 41.2,
        "alt_mean": 13.38,
        "alt_median": -0.08
    },
    "time": "Jul 26 2023 21:06:31"
}