{
    "1H": {
        "btc": -0.03,
        "alt_mean": 0.16,
        "alt_median": 0.2
    },
    "24H": {
        "btc": -0.87,
        "alt_mean": -1.04,
        "alt_median": -1.03
    },
    "7D": {
        "btc": 2.12,
        "alt_mean": 1.01,
        "alt_median": 0.29
    },
    "30D": {
        "btc": -2.31,
        "alt_mean": 0.78,
        "alt_median": -2.7
    },
    "200D": {
        "btc": 41.86,
        "alt_mean": 63.81,
        "alt_median": 28.68
    },
    "1Y": {
        "btc": 81.95,
        "alt_mean": 56.92,
        "alt_median": 10.48
    },
    "time": "Feb 04 2024 20:07:09"
}