{
    "1H": {
        "btc": -0.08,
        "alt_mean": 0.0,
        "alt_median": 0.06
    },
    "24H": {
        "btc": -0.73,
        "alt_mean": -1.84,
        "alt_median": -2.01
    },
    "7D": {
        "btc": 6.64,
        "alt_mean": 10.88,
        "alt_median": 8.3
    },
    "30D": {
        "btc": -5.08,
        "alt_mean": -6.47,
        "alt_median": -6.28
    },
    "200D": {
        "btc": 48.1,
        "alt_mean": 13.54,
        "alt_median": 4.41
    },
    "1Y": {
        "btc": 144.77,
        "alt_mean": 131.91,
        "alt_median": 69.83
    },
    "time": "Aug 25 2024 10:09:26"
}