{
    "1H": {
        "btc": 0.23,
        "alt_mean": -0.74,
        "alt_median": -0.47
    },
    "24H": {
        "btc": -0.7,
        "alt_mean": 5.8,
        "alt_median": 2.88
    },
    "7D": {
        "btc": -5.22,
        "alt_mean": 6.39,
        "alt_median": -4.96
    },
    "30D": {
        "btc": -0.08,
        "alt_mean": 64.65,
        "alt_median": 16.18
    },
    "200D": {
        "btc": -17.92,
        "alt_mean": 168.3,
        "alt_median": 37.29
    },
    "1Y": {
        "btc": 357.03,
        "alt_mean": 1626.74,
        "alt_median": 368.08
    },
    "time": "Sep 09 2021 11:05:27"
}