{
    "1H": {
        "btc": 0.31,
        "alt_mean": 0.89,
        "alt_median": 0.86
    },
    "24H": {
        "btc": 1.25,
        "alt_mean": 3.25,
        "alt_median": 2.2
    },
    "7D": {
        "btc": 8.6,
        "alt_mean": 9.23,
        "alt_median": 7.58
    },
    "30D": {
        "btc": 22.56,
        "alt_mean": 10.73,
        "alt_median": 7.02
    },
    "200D": {
        "btc": 17.4,
        "alt_mean": -3.9,
        "alt_median": -7.04
    },
    "1Y": {
        "btc": 115.05,
        "alt_mean": 78.24,
        "alt_median": 56.39
    },
    "time": "Nov 08 2024 00:46:14"
}