{
    "1H": {
        "btc": -0.2,
        "alt_mean": 0.13,
        "alt_median": -0.12
    },
    "24H": {
        "btc": 4.6,
        "alt_mean": 4.71,
        "alt_median": 4.01
    },
    "7D": {
        "btc": 12.73,
        "alt_mean": 7.76,
        "alt_median": 3.71
    },
    "30D": {
        "btc": 39.81,
        "alt_mean": 1.17,
        "alt_median": -0.18
    },
    "200D": {
        "btc": 117.55,
        "alt_mean": 98.51,
        "alt_median": 46.19
    },
    "1Y": {
        "btc": 75.85,
        "alt_mean": 87.67,
        "alt_median": 33.78
    },
    "time": "Nov 09 2020 00:10:06"
}