{
    "1H": {
        "btc": 0.27,
        "alt_mean": 0.43,
        "alt_median": 0.23
    },
    "24H": {
        "btc": 2.02,
        "alt_mean": 4.01,
        "alt_median": 3.19
    },
    "7D": {
        "btc": -7.2,
        "alt_mean": -10.13,
        "alt_median": -9.24
    },
    "30D": {
        "btc": -0.84,
        "alt_mean": -10.34,
        "alt_median": -9.76
    },
    "200D": {
        "btc": 31.62,
        "alt_mean": 37.43,
        "alt_median": 7.36
    },
    "1Y": {
        "btc": 80.82,
        "alt_mean": 88.85,
        "alt_median": 66.6
    },
    "time": "Oct 12 2025 17:08:14"
}