{
    "1H": {
        "btc": 0.56,
        "alt_mean": 1.53,
        "alt_median": 0.8
    },
    "24H": {
        "btc": -1.01,
        "alt_mean": -1.5,
        "alt_median": -2.74
    },
    "7D": {
        "btc": 17.52,
        "alt_mean": 7.07,
        "alt_median": 0.81
    },
    "30D": {
        "btc": 51.5,
        "alt_mean": 20.12,
        "alt_median": 4.92
    },
    "200D": {
        "btc": 187.84,
        "alt_mean": 147.12,
        "alt_median": 75.32
    },
    "1Y": {
        "btc": 267.33,
        "alt_mean": 306.01,
        "alt_median": 115.34
    },
    "time": "Dec 29 2020 19:27:01"
}