{
    "1H": {
        "btc": -0.3,
        "alt_mean": -0.23,
        "alt_median": -0.22
    },
    "24H": {
        "btc": -4.85,
        "alt_mean": -3.47,
        "alt_median": -3.68
    },
    "7D": {
        "btc": 0.34,
        "alt_mean": 0.48,
        "alt_median": -0.0
    },
    "30D": {
        "btc": 3.57,
        "alt_mean": 2.45,
        "alt_median": 0.05
    },
    "200D": {
        "btc": -35.34,
        "alt_mean": -20.87,
        "alt_median": -24.38
    },
    "1Y": {
        "btc": -15.96,
        "alt_mean": -5.18,
        "alt_median": -0.5
    },
    "time": "Mar 19 2026 11:27:52"
}