{
    "1H": {
        "btc": 0.65,
        "alt_mean": 0.69,
        "alt_median": 0.53
    },
    "24H": {
        "btc": 4.13,
        "alt_mean": 4.37,
        "alt_median": 3.44
    },
    "7D": {
        "btc": 0.96,
        "alt_mean": 5.08,
        "alt_median": 1.41
    },
    "30D": {
        "btc": 37.15,
        "alt_mean": 39.09,
        "alt_median": 26.02
    },
    "200D": {
        "btc": 100.01,
        "alt_mean": 138.97,
        "alt_median": 78.95
    },
    "1Y": {
        "btc": 140.48,
        "alt_mean": 178.16,
        "alt_median": 87.43
    },
    "time": "Nov 30 2020 04:05:27"
}