{
    "1H": {
        "btc": 0.16,
        "alt_mean": 0.13,
        "alt_median": 0.1
    },
    "24H": {
        "btc": 3.49,
        "alt_mean": 2.51,
        "alt_median": 2.36
    },
    "7D": {
        "btc": -6.64,
        "alt_mean": -10.76,
        "alt_median": -11.8
    },
    "30D": {
        "btc": 1.08,
        "alt_mean": -0.96,
        "alt_median": -0.46
    },
    "200D": {
        "btc": 45.71,
        "alt_mean": 11.47,
        "alt_median": -0.25
    },
    "1Y": {
        "btc": -29.98,
        "alt_mean": -38.66,
        "alt_median": -43.81
    },
    "time": "Apr 26 2023 05:07:21"
}