{
    "1H": {
        "btc": 0.16,
        "alt_mean": 0.34,
        "alt_median": 0.23
    },
    "24H": {
        "btc": 0.25,
        "alt_mean": 1.04,
        "alt_median": 0.6
    },
    "7D": {
        "btc": 2.36,
        "alt_mean": 1.54,
        "alt_median": 0.2
    },
    "30D": {
        "btc": -3.75,
        "alt_mean": 8.28,
        "alt_median": 0.71
    },
    "200D": {
        "btc": 15.55,
        "alt_mean": 24.63,
        "alt_median": 5.58
    },
    "1Y": {
        "btc": 97.48,
        "alt_mean": 109.9,
        "alt_median": 82.6
    },
    "time": "Sep 06 2025 00:50:36"
}