{
    "1H": {
        "btc": 0.04,
        "alt_mean": -0.1,
        "alt_median": -0.06
    },
    "24H": {
        "btc": 0.12,
        "alt_mean": -1.12,
        "alt_median": -1.31
    },
    "7D": {
        "btc": -0.92,
        "alt_mean": -2.59,
        "alt_median": -1.85
    },
    "30D": {
        "btc": 8.38,
        "alt_mean": 4.78,
        "alt_median": 0.56
    },
    "200D": {
        "btc": 80.15,
        "alt_mean": 82.82,
        "alt_median": 46.99
    },
    "1Y": {
        "btc": 149.18,
        "alt_mean": 174.7,
        "alt_median": 95.56
    },
    "time": "Jun 02 2024 22:07:17"
}