{
    "1h": {
        "btc": 0.1,
        "alt_mean": 0.0,
        "alt_median": 0.02
    },
    "24h": {
        "btc": 0.2,
        "alt_mean": 1.11,
        "alt_median": 0.09
    },
    "7d": {
        "btc": -0.96,
        "alt_mean": 0.12,
        "alt_median": -0.28
    },
    "30d": {
        "btc": -10.33,
        "alt_mean": 7.81,
        "alt_median": -4.03
    },
    "200d": {
        "btc": 7.37,
        "alt_mean": 49.59,
        "alt_median": 6.8
    },
    "1y": {
        "btc": 2.3,
        "alt_mean": 125.31,
        "alt_median": 39.65
    },
    "time": "Sep 12 2020 00:11:10"
}