{
    "1H": {
        "btc": 0.46,
        "alt_mean": 0.89,
        "alt_median": 0.85
    },
    "24H": {
        "btc": -0.42,
        "alt_mean": -0.33,
        "alt_median": -0.15
    },
    "7D": {
        "btc": -3.98,
        "alt_mean": -1.64,
        "alt_median": -1.86
    },
    "30D": {
        "btc": 7.43,
        "alt_mean": 11.61,
        "alt_median": 4.65
    },
    "200D": {
        "btc": 81.47,
        "alt_mean": 116.77,
        "alt_median": 59.4
    },
    "1Y": {
        "btc": 144.04,
        "alt_mean": 183.53,
        "alt_median": 99.51
    },
    "time": "May 29 2024 17:07:41"
}