{
    "1H": {
        "btc": -0.38,
        "alt_mean": -0.52,
        "alt_median": -0.5
    },
    "24H": {
        "btc": -0.34,
        "alt_mean": -4.73,
        "alt_median": -4.66
    },
    "7D": {
        "btc": -2.48,
        "alt_mean": -10.11,
        "alt_median": -9.84
    },
    "30D": {
        "btc": -2.66,
        "alt_mean": -12.22,
        "alt_median": -17.72
    },
    "200D": {
        "btc": 68.98,
        "alt_mean": 36.58,
        "alt_median": 10.38
    },
    "1Y": {
        "btc": 146.75,
        "alt_mean": 156.57,
        "alt_median": 96.46
    },
    "time": "Jun 18 2024 10:09:01"
}