{
    "1H": {
        "btc": 0.05,
        "alt_mean": -0.12,
        "alt_median": -0.02
    },
    "24H": {
        "btc": 1.5,
        "alt_mean": 1.73,
        "alt_median": 1.35
    },
    "7D": {
        "btc": 2.53,
        "alt_mean": -4.06,
        "alt_median": -3.26
    },
    "30D": {
        "btc": 22.6,
        "alt_mean": 24.14,
        "alt_median": 16.26
    },
    "200D": {
        "btc": 53.13,
        "alt_mean": 52.87,
        "alt_median": 14.16
    },
    "1Y": {
        "btc": 49.85,
        "alt_mean": 35.25,
        "alt_median": 0.05
    },
    "time": "May 21 2025 12:21:43"
}