{
    "1H": {
        "btc": 1.93,
        "alt_mean": 1.79,
        "alt_median": 1.75
    },
    "24H": {
        "btc": 3.43,
        "alt_mean": 4.02,
        "alt_median": 3.4
    },
    "7D": {
        "btc": -0.13,
        "alt_mean": -4.9,
        "alt_median": -5.12
    },
    "30D": {
        "btc": -5.1,
        "alt_mean": 3.04,
        "alt_median": -7.12
    },
    "200D": {
        "btc": -24.41,
        "alt_mean": 123.54,
        "alt_median": 27.97
    },
    "1Y": {
        "btc": 317.08,
        "alt_mean": 1466.22,
        "alt_median": 577.1
    },
    "time": "Oct 01 2021 08:08:08"
}