{
    "1H": {
        "btc": 0.29,
        "alt_mean": -0.25,
        "alt_median": -0.01
    },
    "24H": {
        "btc": 5.33,
        "alt_mean": 9.8,
        "alt_median": 9.42
    },
    "7D": {
        "btc": 6.28,
        "alt_mean": 6.27,
        "alt_median": 4.51
    },
    "30D": {
        "btc": 33.23,
        "alt_mean": 30.27,
        "alt_median": 29.11
    },
    "200D": {
        "btc": 49.29,
        "alt_mean": 40.29,
        "alt_median": 4.11
    },
    "1Y": {
        "btc": 66.91,
        "alt_mean": 44.12,
        "alt_median": 5.89
    },
    "time": "May 08 2025 22:10:34"
}