{
    "1H": {
        "btc": -0.22,
        "alt_mean": -0.17,
        "alt_median": -0.18
    },
    "24H": {
        "btc": -0.07,
        "alt_mean": -0.19,
        "alt_median": -0.02
    },
    "7D": {
        "btc": 0.78,
        "alt_mean": 1.6,
        "alt_median": -0.28
    },
    "30D": {
        "btc": 2.74,
        "alt_mean": -1.54,
        "alt_median": -2.18
    },
    "200D": {
        "btc": 18.64,
        "alt_mean": -13.3,
        "alt_median": -16.98
    },
    "1Y": {
        "btc": 38.23,
        "alt_mean": -2.75,
        "alt_median": -8.3
    },
    "time": "Sep 22 2023 13:09:24"
}