{
    "1H": {
        "btc": 0.13,
        "alt_mean": 0.91,
        "alt_median": 0.88
    },
    "24H": {
        "btc": -5.84,
        "alt_mean": -3.31,
        "alt_median": -4.71
    },
    "7D": {
        "btc": -9.71,
        "alt_mean": -9.1,
        "alt_median": -9.85
    },
    "30D": {
        "btc": -20.07,
        "alt_mean": -9.27,
        "alt_median": -20.05
    },
    "200D": {
        "btc": 14.26,
        "alt_mean": 86.04,
        "alt_median": 0.26
    },
    "1Y": {
        "btc": 163.15,
        "alt_mean": 6460.87,
        "alt_median": 510.23
    },
    "time": "Dec 05 2021 04:08:58"
}