{
    "1H": {
        "btc": 0.03,
        "alt_mean": 0.14,
        "alt_median": 0.03
    },
    "24H": {
        "btc": 0.42,
        "alt_mean": 1.13,
        "alt_median": 0.21
    },
    "7D": {
        "btc": 10.54,
        "alt_mean": 11.34,
        "alt_median": 11.77
    },
    "30D": {
        "btc": 7.41,
        "alt_mean": -1.86,
        "alt_median": -2.26
    },
    "200D": {
        "btc": 49.49,
        "alt_mean": 40.47,
        "alt_median": 3.38
    },
    "1Y": {
        "btc": 46.08,
        "alt_mean": 30.31,
        "alt_median": 0.1
    },
    "time": "Apr 25 2025 00:54:19"
}