{
    "1H": {
        "btc": 0.94,
        "alt_mean": 0.66,
        "alt_median": 0.65
    },
    "24H": {
        "btc": 0.92,
        "alt_mean": -0.05,
        "alt_median": -0.22
    },
    "7D": {
        "btc": 5.63,
        "alt_mean": -1.2,
        "alt_median": -1.64
    },
    "30D": {
        "btc": 10.43,
        "alt_mean": 6.22,
        "alt_median": 4.38
    },
    "200D": {
        "btc": -37.0,
        "alt_mean": -12.48,
        "alt_median": -22.42
    },
    "1Y": {
        "btc": -61.35,
        "alt_mean": -56.22,
        "alt_median": -63.84
    },
    "time": "Dec 14 2022 15:07:46"
}