{
    "1H": {
        "btc": 0.09,
        "alt_mean": 0.42,
        "alt_median": 0.28
    },
    "24H": {
        "btc": -4.89,
        "alt_mean": -4.91,
        "alt_median": -4.99
    },
    "7D": {
        "btc": -6.8,
        "alt_mean": -4.25,
        "alt_median": -7.72
    },
    "30D": {
        "btc": -11.54,
        "alt_mean": -9.11,
        "alt_median": -12.18
    },
    "200D": {
        "btc": 41.53,
        "alt_mean": 586.22,
        "alt_median": 144.22
    },
    "1Y": {
        "btc": 257.23,
        "alt_mean": 739.47,
        "alt_median": 212.65
    },
    "time": "Jul 12 2021 22:04:56"
}