{
    "1H": {
        "btc": 0.31,
        "alt_mean": 0.48,
        "alt_median": 0.42
    },
    "24H": {
        "btc": 3.75,
        "alt_mean": 4.06,
        "alt_median": 2.62
    },
    "7D": {
        "btc": 10.56,
        "alt_mean": 17.87,
        "alt_median": 14.92
    },
    "30D": {
        "btc": 16.08,
        "alt_mean": 31.91,
        "alt_median": 20.48
    },
    "200D": {
        "btc": -53.15,
        "alt_mean": -53.33,
        "alt_median": -64.19
    },
    "1Y": {
        "btc": -30.73,
        "alt_mean": -11.59,
        "alt_median": -20.72
    },
    "time": "Jul 19 2022 03:20:38"
}