{
    "1H": {
        "btc": 0.72,
        "alt_mean": -0.01,
        "alt_median": -0.02
    },
    "24H": {
        "btc": -4.2,
        "alt_mean": -7.72,
        "alt_median": -8.52
    },
    "7D": {
        "btc": 9.6,
        "alt_mean": -1.92,
        "alt_median": -2.42
    },
    "30D": {
        "btc": 11.8,
        "alt_mean": -5.99,
        "alt_median": -6.88
    },
    "200D": {
        "btc": 20.13,
        "alt_mean": 3.1,
        "alt_median": -0.06
    },
    "1Y": {
        "btc": -38.62,
        "alt_mean": -37.0,
        "alt_median": -44.94
    },
    "time": "Mar 15 2023 18:10:01"
}