{
    "1H": {
        "btc": 0.07,
        "alt_mean": 0.06,
        "alt_median": -0.03
    },
    "24H": {
        "btc": -1.13,
        "alt_mean": -1.31,
        "alt_median": -1.05
    },
    "7D": {
        "btc": -6.71,
        "alt_mean": -8.52,
        "alt_median": -10.67
    },
    "30D": {
        "btc": 18.67,
        "alt_mean": 16.31,
        "alt_median": 7.98
    },
    "200D": {
        "btc": 107.64,
        "alt_mean": 142.74,
        "alt_median": 61.94
    },
    "1Y": {
        "btc": 150.64,
        "alt_mean": 286.57,
        "alt_median": 87.34
    },
    "time": "Dec 11 2020 23:04:39"
}