{
    "1H": {
        "btc": 0.3,
        "alt_mean": 0.22,
        "alt_median": 0.2
    },
    "24H": {
        "btc": 8.48,
        "alt_mean": 2.74,
        "alt_median": 2.57
    },
    "7D": {
        "btc": 8.03,
        "alt_mean": 0.38,
        "alt_median": 0.0
    },
    "30D": {
        "btc": 10.63,
        "alt_mean": -3.46,
        "alt_median": -3.24
    },
    "200D": {
        "btc": 12.02,
        "alt_mean": -1.93,
        "alt_median": -2.74
    },
    "1Y": {
        "btc": -36.03,
        "alt_mean": -33.88,
        "alt_median": -42.82
    },
    "time": "Mar 14 2023 00:37:10"
}