{
    "1H": {
        "btc": 0.04,
        "alt_mean": 0.22,
        "alt_median": 0.12
    },
    "24H": {
        "btc": -1.26,
        "alt_mean": -1.34,
        "alt_median": -1.49
    },
    "7D": {
        "btc": 1.1,
        "alt_mean": 1.45,
        "alt_median": 1.16
    },
    "30D": {
        "btc": -9.76,
        "alt_mean": -8.73,
        "alt_median": -10.93
    },
    "200D": {
        "btc": -54.97,
        "alt_mean": -47.49,
        "alt_median": -55.84
    },
    "1Y": {
        "btc": -65.03,
        "alt_mean": -55.79,
        "alt_median": -63.94
    },
    "time": "Oct 10 2022 16:16:50"
}