{
    "1H": {
        "btc": -0.53,
        "alt_mean": -0.39,
        "alt_median": -0.45
    },
    "24H": {
        "btc": -0.33,
        "alt_mean": 0.06,
        "alt_median": 0.03
    },
    "7D": {
        "btc": 3.32,
        "alt_mean": 6.74,
        "alt_median": 6.37
    },
    "30D": {
        "btc": -5.62,
        "alt_mean": -0.33,
        "alt_median": -1.62
    },
    "200D": {
        "btc": 13.31,
        "alt_mean": -11.33,
        "alt_median": -21.54
    },
    "1Y": {
        "btc": 121.19,
        "alt_mean": 126.17,
        "alt_median": 61.27
    },
    "time": "Sep 13 2024 12:16:49"
}