{
    "1H": {
        "btc": 0.13,
        "alt_mean": 0.39,
        "alt_median": 0.19
    },
    "24H": {
        "btc": 6.72,
        "alt_mean": 6.45,
        "alt_median": 6.76
    },
    "7D": {
        "btc": 10.91,
        "alt_mean": 10.09,
        "alt_median": 10.08
    },
    "30D": {
        "btc": 8.86,
        "alt_mean": 0.03,
        "alt_median": 0.0
    },
    "200D": {
        "btc": 49.28,
        "alt_mean": 40.39,
        "alt_median": 2.93
    },
    "1Y": {
        "btc": 38.61,
        "alt_mean": 22.66,
        "alt_median": -1.5
    },
    "time": "Apr 22 2025 23:09:42"
}