{
    "1H": {
        "btc": 0.02,
        "alt_mean": -0.21,
        "alt_median": -0.12
    },
    "24H": {
        "btc": 0.09,
        "alt_mean": 3.09,
        "alt_median": 1.5
    },
    "7D": {
        "btc": 6.66,
        "alt_mean": 16.74,
        "alt_median": 8.05
    },
    "30D": {
        "btc": 56.93,
        "alt_mean": 63.99,
        "alt_median": 48.63
    },
    "200D": {
        "btc": 156.54,
        "alt_mean": 220.05,
        "alt_median": 139.09
    },
    "1Y": {
        "btc": 199.9,
        "alt_mean": 197.61,
        "alt_median": 112.83
    },
    "time": "Mar 07 2024 12:13:13"
}