{
    "1H": {
        "btc": 0.38,
        "alt_mean": 0.56,
        "alt_median": 0.39
    },
    "24H": {
        "btc": -0.93,
        "alt_mean": -1.73,
        "alt_median": -1.57
    },
    "7D": {
        "btc": -4.15,
        "alt_mean": 2.79,
        "alt_median": -2.03
    },
    "30D": {
        "btc": -5.55,
        "alt_mean": 16.19,
        "alt_median": -4.79
    },
    "200D": {
        "btc": 419.52,
        "alt_mean": 577.51,
        "alt_median": 229.88
    },
    "1Y": {
        "btc": 743.66,
        "alt_mean": 2228.99,
        "alt_median": 668.27
    },
    "time": "Mar 24 2021 02:26:27"
}