{
    "1H": {
        "btc": 0.54,
        "alt_mean": 0.69,
        "alt_median": 0.6
    },
    "24H": {
        "btc": -1.88,
        "alt_mean": -0.2,
        "alt_median": -0.36
    },
    "7D": {
        "btc": 0.24,
        "alt_mean": 5.04,
        "alt_median": 1.71
    },
    "30D": {
        "btc": 13.36,
        "alt_mean": 22.78,
        "alt_median": 13.35
    },
    "200D": {
        "btc": -46.88,
        "alt_mean": -47.51,
        "alt_median": -60.02
    },
    "1Y": {
        "btc": -40.15,
        "alt_mean": -22.76,
        "alt_median": -35.75
    },
    "time": "Aug 04 2022 10:09:29"
}