{
    "1H": {
        "btc": -0.22,
        "alt_mean": -0.61,
        "alt_median": -0.48
    },
    "24H": {
        "btc": -1.7,
        "alt_mean": -1.84,
        "alt_median": -1.8
    },
    "7D": {
        "btc": -1.53,
        "alt_mean": -3.77,
        "alt_median": -3.94
    },
    "30D": {
        "btc": -3.26,
        "alt_mean": -16.85,
        "alt_median": -21.78
    },
    "200D": {
        "btc": -49.25,
        "alt_mean": -57.08,
        "alt_median": -65.86
    },
    "1Y": {
        "btc": -20.07,
        "alt_mean": -14.15,
        "alt_median": -34.28
    },
    "time": "Jun 10 2022 09:08:33"
}