{
    "1H": {
        "btc": 0.43,
        "alt_mean": 0.46,
        "alt_median": 0.39
    },
    "24H": {
        "btc": -3.28,
        "alt_mean": -3.29,
        "alt_median": -3.57
    },
    "7D": {
        "btc": 1.66,
        "alt_mean": 3.13,
        "alt_median": 0.63
    },
    "30D": {
        "btc": 1.6,
        "alt_mean": -0.76,
        "alt_median": -1.43
    },
    "200D": {
        "btc": 92.18,
        "alt_mean": 133.24,
        "alt_median": 86.47
    },
    "1Y": {
        "btc": 151.85,
        "alt_mean": 190.98,
        "alt_median": 99.94
    },
    "time": "May 24 2024 10:08:57"
}