{
    "1H": {
        "btc": -0.3,
        "alt_mean": -0.42,
        "alt_median": -0.43
    },
    "24H": {
        "btc": -0.25,
        "alt_mean": 1.17,
        "alt_median": -0.45
    },
    "7D": {
        "btc": -1.86,
        "alt_mean": 5.83,
        "alt_median": 0.62
    },
    "30D": {
        "btc": -4.93,
        "alt_mean": 11.22,
        "alt_median": 0.28
    },
    "200D": {
        "btc": 30.54,
        "alt_mean": 220.68,
        "alt_median": 40.75
    },
    "1Y": {
        "btc": 48.62,
        "alt_mean": 2255.33,
        "alt_median": 282.59
    },
    "time": "Jan 05 2022 11:06:12"
}