{
    "1H": {
        "btc": -0.65,
        "alt_mean": -0.59,
        "alt_median": -0.58
    },
    "24H": {
        "btc": -0.43,
        "alt_mean": -1.16,
        "alt_median": -1.45
    },
    "7D": {
        "btc": 4.0,
        "alt_mean": 2.03,
        "alt_median": 0.22
    },
    "30D": {
        "btc": 11.61,
        "alt_mean": 21.32,
        "alt_median": 10.9
    },
    "200D": {
        "btc": 16.61,
        "alt_mean": 79.48,
        "alt_median": 6.0
    },
    "1Y": {
        "btc": 292.76,
        "alt_mean": 3022.79,
        "alt_median": 595.87
    },
    "time": "Nov 14 2021 19:05:56"
}