{
    "1H": {
        "btc": -1.16,
        "alt_mean": -1.3,
        "alt_median": -1.38
    },
    "24H": {
        "btc": 4.66,
        "alt_mean": 6.82,
        "alt_median": 5.38
    },
    "7D": {
        "btc": -0.94,
        "alt_mean": 2.33,
        "alt_median": 0.45
    },
    "30D": {
        "btc": -31.75,
        "alt_mean": -19.06,
        "alt_median": -26.05
    },
    "200D": {
        "btc": 142.54,
        "alt_mean": 1198.61,
        "alt_median": 301.43
    },
    "1Y": {
        "btc": 310.27,
        "alt_mean": 1803.06,
        "alt_median": 437.94
    },
    "time": "Jun 03 2021 11:48:04"
}