{
    "1H": {
        "btc": 0.52,
        "alt_mean": 0.4,
        "alt_median": 0.34
    },
    "24H": {
        "btc": 5.59,
        "alt_mean": 2.97,
        "alt_median": 3.26
    },
    "7D": {
        "btc": 3.17,
        "alt_mean": 3.51,
        "alt_median": 3.11
    },
    "30D": {
        "btc": 0.6,
        "alt_mean": 1.39,
        "alt_median": -0.52
    },
    "200D": {
        "btc": -48.84,
        "alt_mean": -40.43,
        "alt_median": -46.69
    },
    "1Y": {
        "btc": -53.41,
        "alt_mean": -46.15,
        "alt_median": -57.3
    },
    "time": "Sep 27 2022 15:12:53"
}