{
    "1H": {
        "btc": 0.18,
        "alt_mean": 0.01,
        "alt_median": 0.05
    },
    "24H": {
        "btc": -0.98,
        "alt_mean": -0.85,
        "alt_median": -0.74
    },
    "7D": {
        "btc": -8.58,
        "alt_mean": -8.27,
        "alt_median": -9.04
    },
    "30D": {
        "btc": -12.08,
        "alt_mean": -17.09,
        "alt_median": -18.39
    },
    "200D": {
        "btc": -21.12,
        "alt_mean": 8.58,
        "alt_median": -17.82
    },
    "1Y": {
        "btc": -30.65,
        "alt_mean": 92.87,
        "alt_median": 3.91
    },
    "time": "Mar 11 2022 18:09:49"
}