{
    "1H": {
        "btc": 0.47,
        "alt_mean": 0.42,
        "alt_median": 0.41
    },
    "24H": {
        "btc": -1.85,
        "alt_mean": -0.03,
        "alt_median": -0.16
    },
    "7D": {
        "btc": -2.53,
        "alt_mean": 5.03,
        "alt_median": 3.07
    },
    "30D": {
        "btc": 7.61,
        "alt_mean": 3.59,
        "alt_median": 0.04
    },
    "200D": {
        "btc": 3.53,
        "alt_mean": 480.75,
        "alt_median": 89.52
    },
    "1Y": {
        "btc": 239.13,
        "alt_mean": 713.01,
        "alt_median": 203.78
    },
    "time": "Aug 04 2021 11:05:08"
}