{
    "1H": {
        "btc": 0.18,
        "alt_mean": 0.15,
        "alt_median": 0.12
    },
    "24H": {
        "btc": 0.13,
        "alt_mean": 0.21,
        "alt_median": -0.15
    },
    "7D": {
        "btc": 1.77,
        "alt_mean": -1.63,
        "alt_median": -1.82
    },
    "30D": {
        "btc": -10.88,
        "alt_mean": -13.68,
        "alt_median": -13.54
    },
    "200D": {
        "btc": 13.9,
        "alt_mean": -15.77,
        "alt_median": -24.66
    },
    "1Y": {
        "btc": 16.17,
        "alt_mean": -12.87,
        "alt_median": -11.75
    },
    "time": "Sep 13 2023 12:13:33"
}