{
    "1H": {
        "btc": -0.16,
        "alt_mean": -0.15,
        "alt_median": -0.19
    },
    "24H": {
        "btc": -4.31,
        "alt_mean": -4.97,
        "alt_median": -5.31
    },
    "7D": {
        "btc": 11.22,
        "alt_mean": 13.13,
        "alt_median": 11.09
    },
    "30D": {
        "btc": 0.71,
        "alt_mean": -10.97,
        "alt_median": -12.65
    },
    "200D": {
        "btc": 46.76,
        "alt_mean": 11.88,
        "alt_median": -0.01
    },
    "1Y": {
        "btc": 99.08,
        "alt_mean": 75.52,
        "alt_median": 35.79
    },
    "time": "Aug 12 2024 06:13:29"
}