{
    "1H": {
        "btc": -0.02,
        "alt_mean": -0.02,
        "alt_median": -0.07
    },
    "24H": {
        "btc": -2.11,
        "alt_mean": -0.71,
        "alt_median": -1.23
    },
    "7D": {
        "btc": -3.21,
        "alt_mean": 12.79,
        "alt_median": 6.7
    },
    "30D": {
        "btc": 31.17,
        "alt_mean": 63.18,
        "alt_median": 38.15
    },
    "200D": {
        "btc": 54.91,
        "alt_mean": 52.92,
        "alt_median": 22.04
    },
    "1Y": {
        "btc": 148.47,
        "alt_mean": 172.15,
        "alt_median": 104.84
    },
    "time": "Nov 28 2024 20:11:26"
}