{
    "1H": {
        "btc": 0.13,
        "alt_mean": 0.3,
        "alt_median": 0.19
    },
    "24H": {
        "btc": 2.72,
        "alt_mean": 1.16,
        "alt_median": 0.7
    },
    "7D": {
        "btc": 8.62,
        "alt_mean": 14.23,
        "alt_median": 12.84
    },
    "30D": {
        "btc": 2.84,
        "alt_mean": 2.5,
        "alt_median": -7.01
    },
    "200D": {
        "btc": 60.13,
        "alt_mean": 109.31,
        "alt_median": 52.41
    },
    "1Y": {
        "btc": 131.28,
        "alt_mean": 296.21,
        "alt_median": 118.11
    },
    "time": "Jan 07 2025 09:10:46"
}