{
    "1H": {
        "btc": -0.35,
        "alt_mean": -0.06,
        "alt_median": -0.22
    },
    "24H": {
        "btc": 7.08,
        "alt_mean": 3.96,
        "alt_median": 3.41
    },
    "7D": {
        "btc": 10.27,
        "alt_mean": 12.93,
        "alt_median": 8.38
    },
    "30D": {
        "btc": 8.84,
        "alt_mean": 65.46,
        "alt_median": 38.43
    },
    "200D": {
        "btc": 292.37,
        "alt_mean": 249.05,
        "alt_median": 109.26
    },
    "1Y": {
        "btc": 284.72,
        "alt_mean": 364.23,
        "alt_median": 98.69
    },
    "time": "Feb 03 2021 01:37:02"
}