{
    "1H": {
        "btc": -0.1,
        "alt_mean": 0.1,
        "alt_median": 0.08
    },
    "24H": {
        "btc": 2.14,
        "alt_mean": 2.58,
        "alt_median": 1.79
    },
    "7D": {
        "btc": 1.3,
        "alt_mean": 2.65,
        "alt_median": 1.59
    },
    "30D": {
        "btc": 28.62,
        "alt_mean": 16.13,
        "alt_median": 10.04
    },
    "200D": {
        "btc": -1.33,
        "alt_mean": 76.03,
        "alt_median": -0.07
    },
    "1Y": {
        "btc": 349.76,
        "alt_mean": 2366.74,
        "alt_median": 824.84
    },
    "time": "Nov 01 2021 10:07:36"
}